pyrseas/__init__.py
pyrseas/augmentdb.py
pyrseas/cmdargs.py
pyrseas/config.py
pyrseas/config.yaml
pyrseas/database.py
pyrseas/dbaugment.py
pyrseas/dbtoyaml.py
pyrseas/testutils.py
pyrseas/yamltodb.py
pyrseas/yamlutil.py
pyrseas/augment/__init__.py
pyrseas/augment/audit.py
pyrseas/augment/column.py
pyrseas/augment/function.py
pyrseas/augment/schema.py
pyrseas/augment/table.py
pyrseas/augment/trigger.py
pyrseas/dbobject/__init__.py
pyrseas/dbobject/cast.py
pyrseas/dbobject/collation.py
pyrseas/dbobject/column.py
pyrseas/dbobject/constraint.py
pyrseas/dbobject/conversion.py
pyrseas/dbobject/dbtype.py
pyrseas/dbobject/eventtrig.py
pyrseas/dbobject/extension.py
pyrseas/dbobject/foreign.py
pyrseas/dbobject/function.py
pyrseas/dbobject/index.py
pyrseas/dbobject/language.py
pyrseas/dbobject/operator.py
pyrseas/dbobject/operclass.py
pyrseas/dbobject/operfamily.py
pyrseas/dbobject/privileges.py
pyrseas/dbobject/rule.py
pyrseas/dbobject/schema.py
pyrseas/dbobject/table.py
pyrseas/dbobject/textsearch.py
pyrseas/dbobject/trigger.py
pyrseas/dbobject/view.py
pyrseas/lib/__init__.py
pyrseas/lib/dbutils.py
pyrseas/lib/pycompat.py
Pyrseas-0.9.1.dist-info/AUTHORS.rst
Pyrseas-0.9.1.dist-info/LICENSE
Pyrseas-0.9.1.dist-info/METADATA
Pyrseas-0.9.1.dist-info/WHEEL
Pyrseas-0.9.1.dist-info/entry_points.txt
Pyrseas-0.9.1.dist-info/top_level.txt
Pyrseas-0.9.1.dist-info/RECORD
