Metadata-Version: 2.1
Name: Pyrseas
Version: 0.9.1
Summary: Utilities to assist in database schema versioning
Home-page: https://perseas.github.io/
Author: Joe Abbate
Author-email: jma@freedomcircle.com
License: BSD
Platform: OS-independent
Classifier: Development Status :: 4 - Beta
Classifier: Environment :: Console
Classifier: Intended Audience :: Developers
Classifier: Intended Audience :: Information Technology
Classifier: Intended Audience :: System Administrators
Classifier: License :: OSI Approved :: BSD License
Classifier: Natural Language :: English
Classifier: Operating System :: OS Independent
Classifier: Programming Language :: Python
Classifier: Programming Language :: Python :: 2
Classifier: Programming Language :: Python :: 2.7
Classifier: Programming Language :: Python :: 3
Classifier: Programming Language :: Python :: 3.4
Classifier: Programming Language :: Python :: 3.5
Classifier: Programming Language :: Python :: 3.6
Classifier: Programming Language :: Python :: 3.7
Classifier: Programming Language :: SQL
Classifier: Topic :: Database :: Front-Ends
Classifier: Topic :: Software Development :: Code Generators
Classifier: Topic :: Software Development :: Version Control
Requires-Dist: PyYAML (>=3.10)
Requires-Dist: pgdbconn (>=0.8.0)
Requires-Dist: psycopg2 (>=2.5)
